README.md
setup.py
aceshipro.egg-info/PKG-INFO
aceshipro.egg-info/SOURCES.txt
aceshipro.egg-info/dependency_links.txt
aceshipro.egg-info/requires.txt
aceshipro.egg-info/top_level.txt
star/__init__.py
star/test1.py
star/test2.py