Metadata-Version: 2.1
Name: aceshipro
Version: 0.1
Home-page: https://pypi.org/search/?q=mathnet
Author: Jianxing Wang
Author-email: wjx_ncepu@126.com
Maintainer: Jianxing Wang
Maintainer-email: wjx_ncepu@126.com
License: MIT License
Classifier: Development Status :: 3 - Alpha
Classifier: Intended Audience :: Developers
Classifier: Topic :: Software Development :: Build Tools
Classifier: License :: OSI Approved :: MIT License
Classifier: Programming Language :: Python :: 3
Requires-Python: >=3.0
Requires-Dist: PyPDF2
Requires-Dist: removebg
Requires-Dist: seaborn
Requires-Dist: pandas
